README.md
setup.py
pocdb/__init__.py
pocdb/models/__init__.py
pocdb/models/api.py
pocdb/utils/__init__.py
pocdb_py.egg-info/PKG-INFO
pocdb_py.egg-info/SOURCES.txt
pocdb_py.egg-info/dependency_links.txt
pocdb_py.egg-info/not-zip-safe
pocdb_py.egg-info/requires.txt
pocdb_py.egg-info/top_level.txt