Metadata-Version: 1.0
Name: pocdb-py
Version: 0.6
Summary: pocdb.com Python SDK
Home-page: https://github.com/jeffthorne/pocdb-py
Author: Jeff Thorne
Author-email: jthorne@u.washington.edu
License: MIT
Platform: UNKNOWN
